dataVisualisation/__init__.py
dataVisualisation-0.0.1.dist-info/LICENSE.txt
dataVisualisation-0.0.1.dist-info/METADATA
dataVisualisation-0.0.1.dist-info/WHEEL
dataVisualisation-0.0.1.dist-info/top_level.txt
dataVisualisation-0.0.1.dist-info/RECORD
