Metadata-Version: 2.1
Name: dataVisualisation
Version: 0.0.1
Summary: Linear Regression
Home-page: UNKNOWN
Author: ramscodehub
Author-email: ywolf217@gmail.com
License: UNKNOWN
Platform: UNKNOWN
Classifier: Programming Language :: Python :: 3
Classifier: License :: OSI Approved :: MIT License
Classifier: Operating System :: OS Independent
